[
    {
        "mail_address": "P.O. Box 942873,Sacramento, CA 94273-0001",
        "mail_city": "Sacramento",
        "mail_phone": null,
        "mail_pobox": "942873",
        "mail_state": "CA",
        "mail_to": null,
        "mail_zip": "94273-0001",
        "office_address": "1120 N Street,Sacramento, CA 95814",
        "office_city": "Sacramento",
        "office_link": null,
        "office_name": "Headquarters :- Sacramento",
        "office_phone": "General Information:  (916) 654-2852  Public Affairs/Media Line:  (916) 657-5060",
        "office_state": "CA",
        "office_zip": "95814"
    },
    {
        "mail_address": "P.O. Box 3700,Eureka, CA 95502-3700",
        "mail_city": "Eureka",
        "mail_phone": null,
        "mail_pobox": "3700",
        "mail_state": "CA",
        "mail_to": null,
        "mail_zip": "95502-3700",
        "office_address": "1656 Union Street,Eureka, CA 95501",
        "office_city": "Eureka",
        "office_link": "https://dot.ca.gov//caltrans-near-me/district-1",
        "office_name": "District 1 - Eureka",
        "office_phone": "(707) 445-6600",
        "office_state": "CA",
        "office_zip": "95501"
    },
    {
        "mail_address": "1657 Riverside Drive,Redding, CA 96001",
        "mail_city": "Redding",
        "mail_phone": null,
        "mail_pobox": null,
        "mail_state": "CA",
        "mail_to": "mailto:d2pio@dot.ca.gov",
        "mail_zip": "96001",
        "office_address": "1657 Riverside Drive,Redding, CA 96001",
        "office_city": "Redding",
        "office_link": "https://dot.ca.gov//caltrans-near-me/district-2",
        "office_name": "District 2 - Redding",
        "office_phone": "(530) 225-3426",
        "office_state": "CA",
        "office_zip": "96001"
    },
    {
        "mail_address": "703 B Street,Marysville, CA 95901",
        "mail_city": "Marysville",
        "mail_phone": null,
        "mail_pobox": null,
        "mail_state": "CA",
        "mail_to": "mailto:d3pio@dot.ca.gov",
        "mail_zip": "95901",
        "office_address": "703 B Street,Marysville, CA 95901",
        "office_city": "Marysville",
        "office_link": "https://dot.ca.gov//caltrans-near-me/district-3",
        "office_name": "District 3 - Marysville / Sacramento",
        "office_phone": "(530) 741-4572",
        "office_state": "CA",
        "office_zip": "95901"
    },
    {
        "mail_address": "P.O. Box 23660,Oakland, CA 94623-0660",
        "mail_city": "Oakland",
        "mail_phone": null,
        "mail_pobox": "23660",
        "mail_state": "CA",
        "mail_to": "mailto:caltrans_d4@dot.ca.gov",
        "mail_zip": "94623-0660",
        "office_address": "111 Grand Ave,Oakland, CA 94612",
        "office_city": "Oakland",
        "office_link": "https://dot.ca.gov//caltrans-near-me/district-4",
        "office_name": "District 4 - Bay Area / Oakland",
        "office_phone": "(510) 286-4444",
        "office_state": "CA",
        "office_zip": "94612"
    },
    {
        "mail_address": "50 Higuera Street,San Luis Obispo, CA 93401-5415",
        "mail_city": "San Luis Obispo",
        "mail_phone": null,
        "mail_pobox": null,
        "mail_state": "CA",
        "mail_to": "mailto:info-d5@dot.ca.gov",
        "mail_zip": "93401-5415",
        "office_address": "50 Higuera Street,San Luis Obispo, CA 93401-5415",
        "office_city": "San Luis Obispo",
        "office_link": "https://dot.ca.gov//caltrans-near-me/district-5",
        "office_name": "District 5 - San Luis Obispo / Santa Barbara",
        "office_phone": "(805) 549-3111",
        "office_state": "CA",
        "office_zip": "93401-5415"
    },
    {
        "mail_address": "P.O. Box 12616,Fresno, CA 93778-2616",
        "mail_city": "Fresno",
        "mail_phone": null,
        "mail_pobox": "12616",
        "mail_state": "CA",
        "mail_to": "mailto:d6.public.info@dot.ca.gov",
        "mail_zip": "93778-2616",
        "office_address": "1352 W. Olive Avenue,Fresno, CA 93728",
        "office_city": "Fresno",
        "office_link": "https://dot.ca.gov//caltrans-near-me/district-6",
        "office_name": "District 6 - Fresno / Bakersfield",
        "office_phone": "(559) 444-2518",
        "office_state": "CA",
        "office_zip": "93728"
    },
    {
        "mail_address": "100 South Main Street,Los Angeles, CA 90012",
        "mail_city": "Los Angeles",
        "mail_phone": null,
        "mail_pobox": null,
        "mail_state": "CA",
        "mail_to": "mailto:d7inquiries@dot.ca.gov",
        "mail_zip": "90012",
        "office_address": "100 South Main Street,Los Angeles, CA 90012",
        "office_city": "Los Angeles",
        "office_link": "https://dot.ca.gov//caltrans-near-me/district-7",
        "office_name": "District 7 - Los Angeles",
        "office_phone": "(213) 897-3656",
        "office_state": "CA",
        "office_zip": "90012"
    },
    {
        "mail_address": "464 W. 4th Street,Attn: Public Affairs,            San Bernardino",
        "mail_city": "Attn: Public Affairs",
        "mail_phone": null,
        "mail_pobox": null,
        "mail_state": "San",
        "mail_to": null,
        "mail_zip": "Bernardino",
        "office_address": "464 W. 4th Street,San Bernardino, CA 92401",
        "office_city": "San Bernardino",
        "office_link": "https://dot.ca.gov//caltrans-near-me/district-8",
        "office_name": "District 8 - San Bernardino / Riverside",
        "office_phone": "(909) 383-4631",
        "office_state": "CA",
        "office_zip": "92401"
    },
    {
        "mail_address": "500 South Main Street,Bishop, CA 93514",
        "mail_city": "Bishop",
        "mail_phone": null,
        "mail_pobox": null,
        "mail_state": "CA",
        "mail_to": "mailto:D9PublicInfo@dot.ca.gov",
        "mail_zip": "93514",
        "office_address": "500 South Main Street,Bishop, CA 93514",
        "office_city": "Bishop",
        "office_link": "https://dot.ca.gov//caltrans-near-me/district-9",
        "office_name": "District 9 - Bishop",
        "office_phone": "(760) 872-0601",
        "office_state": "CA",
        "office_zip": "93514"
    },
    {
        "mail_address": "1976 East Dr. Martin Luther King Jr. Blvd.,Stockton, CA 95205",
        "mail_city": "Stockton",
        "mail_phone": null,
        "mail_pobox": null,
        "mail_state": "CA",
        "mail_to": "mailto:district10publicaffairs@dot.ca.gov",
        "mail_zip": "95205",
        "office_address": "1976 East Dr. Martin Luther King Jr. Blvd.,Stockton, CA 95205",
        "office_city": "Stockton",
        "office_link": "https://dot.ca.gov//caltrans-near-me/district-10",
        "office_name": "District 10 - Stockton",
        "office_phone": "(209) 948-7543",
        "office_state": "CA",
        "office_zip": "95205"
    },
    {
        "mail_address": "4050 Taylor Street,San Diego, CA 92110",
        "mail_city": "San Diego",
        "mail_phone": null,
        "mail_pobox": null,
        "mail_state": "CA",
        "mail_to": "mailto:ct.public.information.d11@dot.ca.gov",
        "mail_zip": "92110",
        "office_address": "4050 Taylor Street,San Diego, CA 92110",
        "office_city": "San Diego",
        "office_link": "https://dot.ca.gov//caltrans-near-me/district-11",
        "office_name": "District 11 - San Diego",
        "office_phone": "(619) 688-6699",
        "office_state": "CA",
        "office_zip": "92110"
    }
]